metaflow_extensions/dbt_ext/cmd/dbt_cmd.py
metaflow_extensions/dbt_ext/cmd/flow_generator.py
metaflow_extensions/dbt_ext/cmd/mfextinit_dbt_ext.py
metaflow_extensions/dbt_ext/config/mfextinit_dbt_ext.py
metaflow_extensions/dbt_ext/examples/README.md
metaflow_extensions/dbt_ext/examples/docker-compose.yml
metaflow_extensions/dbt_ext/examples/example.profiles.yml
metaflow_extensions/dbt_ext/examples/00-create-database/README.md
metaflow_extensions/dbt_ext/examples/00-create-database/createdbflow.py
metaflow_extensions/dbt_ext/examples/00-create-database/example.config.py
metaflow_extensions/dbt_ext/examples/00-create-database/setup.sh
metaflow_extensions/dbt_ext/examples/01-simple-dbt-flow/README.md
metaflow_extensions/dbt_ext/examples/01-simple-dbt-flow/dbtflow.py
metaflow_extensions/dbt_ext/examples/01-simple-dbt-flow/example.config.py
metaflow_extensions/dbt_ext/examples/01-simple-dbt-flow/setup.sh
metaflow_extensions/dbt_ext/examples/01-simple-dbt-flow/shortdbtflow.py
metaflow_extensions/dbt_ext/examples/02-remote-dbt-flow/README.md
metaflow_extensions/dbt_ext/examples/02-remote-dbt-flow/example.config.py
metaflow_extensions/dbt_ext/examples/02-remote-dbt-flow/remotedbtflow.py
metaflow_extensions/dbt_ext/examples/02-remote-dbt-flow/setup.sh
metaflow_extensions/dbt_ext/examples/03-stateful-dbt-flow/README.md
metaflow_extensions/dbt_ext/examples/03-stateful-dbt-flow/example.config.py
metaflow_extensions/dbt_ext/examples/03-stateful-dbt-flow/setup.sh
metaflow_extensions/dbt_ext/examples/03-stateful-dbt-flow/stateful_remote_dbtflow.py
metaflow_extensions/dbt_ext/examples/04-pandas-duckdb-flow/README.md
metaflow_extensions/dbt_ext/examples/04-pandas-duckdb-flow/data.csv
metaflow_extensions/dbt_ext/examples/04-pandas-duckdb-flow/duckdbflow.py
metaflow_extensions/dbt_ext/examples/04-pandas-duckdb-flow/example.config.py
metaflow_extensions/dbt_ext/examples/04-pandas-duckdb-flow/setup.sh
metaflow_extensions/dbt_ext/examples/05-snowflake-example/README.md
metaflow_dbt-1.0.7.dist-info/LICENSE
metaflow_dbt-1.0.7.dist-info/METADATA
metaflow_dbt-1.0.7.dist-info/WHEEL
metaflow_dbt-1.0.7.dist-info/top_level.txt
metaflow_dbt-1.0.7.dist-info/RECORD
