Metadata-Version: 2.1
Name: metaflow-dbt
Version: 1.0.7
Summary: DBT extension for Metaflow
Author: Outerbounds
Author-email: help@outerbounds.co
License: Apache Software License
Classifier: Development Status :: 4 - Beta
Classifier: License :: OSI Approved :: Apache Software License
Classifier: Operating System :: MacOS :: MacOS X
Classifier: Operating System :: POSIX :: Linux
Classifier: Programming Language :: Python :: 3
Classifier: Programming Language :: Python :: 3.8
Classifier: Programming Language :: Python :: 3.9
Classifier: Programming Language :: Python :: 3.10
Classifier: Programming Language :: Python :: 3.11
Classifier: Programming Language :: Python :: 3.12
Classifier: Programming Language :: Python :: 3.13
Requires-Python: >=3.8
License-File: LICENSE
Requires-Dist: dbt-core>=1.7.0
Requires-Dist: pyyaml
